{
    "appKeys": {},
    "capabilities": [
        ""
    ],
    "companyName": "jirokanayama@gmail.com",
    "enableMultiJS": false,
    "longName": "SHEEP-Color",
    "projectType": "native",
    "resources": {
        "media": [
            {
                "file": "images/bw-bg.png",
                "name": "IMAGE_BG",
                "targetPlatforms": [
                    "aplite",
                    "basalt",
                    "chalk"
                ],
                "type": "bitmap"
            },
            {
                "file": "images/bw-sheep01.png",
                "name": "IMAGE_SHEEP01",
                "type": "bitmap"
            },
            {
                "file": "images/bw-sheep00.png",
                "name": "IMAGE_SHEEP00",
                "type": "bitmap"
            }
        ]
    },
    "sdkVersion": "3",
    "shortName": "SHEEP-Color",
    "targetPlatforms": [
        "basalt",
        "chalk"
    ],
    "uuid": "3b1f3047-d53f-4218-ae30-dd5bb0694f0b",
    "versionLabel": "1.1",
    "watchapp": {
        "watchface": false
    }
}
